sample_mcp/__init__.py
sample_mcp/__main__.py
sample_mcp/mcp_model.py
sample_mcp-0.2.0.dist-info/WHEEL
sample_mcp-0.2.0.dist-info/entry_points.txt
sample_mcp-0.2.0.dist-info/METADATA
sample_mcp-0.2.0.dist-info/RECORD
