Metadata-Version: 2.3
Name: sample-mcp
Version: 0.2.0
Summary: My math tools for operation
Author: Nikitha Uma 
Author-email: Nikitha Uma  <nikithauma63@gmail.com>
Requires-Dist: mcp[cli]>=1.12.3
Requires-Dist: numpy>=2.3.2
Requires-Dist: sympy>=1.14.0
Requires-Python: >=3.11
